[{
  "dateTime" : "09/08/16 00:00:00",
  "value" : "1440"
},{
  "dateTime" : "09/09/16 00:00:00",
  "value" : "561"
},{
  "dateTime" : "09/10/16 00:00:00",
  "value" : "712"
},{
  "dateTime" : "09/11/16 00:00:00",
  "value" : "845"
},{
  "dateTime" : "09/12/16 00:00:00",
  "value" : "942"
},{
  "dateTime" : "09/13/16 00:00:00",
  "value" : "801"
},{
  "dateTime" : "09/14/16 00:00:00",
  "value" : "655"
},{
  "dateTime" : "09/15/16 00:00:00",
  "value" : "769"
},{
  "dateTime" : "09/16/16 00:00:00",
  "value" : "692"
},{
  "dateTime" : "09/17/16 00:00:00",
  "value" : "779"
},{
  "dateTime" : "09/18/16 00:00:00",
  "value" : "677"
},{
  "dateTime" : "09/19/16 00:00:00",
  "value" : "660"
},{
  "dateTime" : "09/20/16 00:00:00",
  "value" : "821"
},{
  "dateTime" : "09/21/16 00:00:00",
  "value" : "1440"
},{
  "dateTime" : "09/22/16 00:00:00",
  "value" : "1440"
},{
  "dateTime" : "09/23/16 00:00:00",
  "value" : "1440"
},{
  "dateTime" : "09/24/16 00:00:00",
  "value" : "1440"
},{
  "dateTime" : "09/25/16 00:00:00",
  "value" : "1440"
},{
  "dateTime" : "09/26/16 00:00:00",
  "value" : "1440"
},{
  "dateTime" : "09/27/16 00:00:00",
  "value" : "1440"
},{
  "dateTime" : "09/28/16 00:00:00",
  "value" : "1440"
},{
  "dateTime" : "09/29/16 00:00:00",
  "value" : "1440"
},{
  "dateTime" : "09/30/16 00:00:00",
  "value" : "1440"
},{
  "dateTime" : "10/01/16 00:00:00",
  "value" : "1440"
},{
  "dateTime" : "10/02/16 00:00:00",
  "value" : "1440"
},{
  "dateTime" : "10/03/16 00:00:00",
  "value" : "1440"
},{
  "dateTime" : "10/04/16 00:00:00",
  "value" : "1005"
},{
  "dateTime" : "10/05/16 00:00:00",
  "value" : "684"
},{
  "dateTime" : "10/06/16 00:00:00",
  "value" : "872"
},{
  "dateTime" : "10/07/16 00:00:00",
  "value" : "701"
}]